{"index.md":"8a547bc8","react_article_react-hook.md":"7da6d3c7","common_index.md":"ffebcb47","css_article_css3.md":"445041ac","css_article_css.md":"e715b59a","js_article_js.md":"874983e7","vue_article_vue-source-code3.md":"8c323f07","html_index.md":"e106ceb9","react_index.md":"2fb40925","js_index.md":"2203c364","common_article_cmd.md":"308d54fa","js_article_es6.md":"af0a44a6","vue_index.md":"d9bb9dc8","vue_article_vue-source-code2.md":"9cbeb21c","html_article_html.md":"3721355c","individual_index.md":"51038ced","react_article_react-source-code.md":"e64bc9b0","common_article_vs.md":"299198ae","css_index.md":"7c9ca31f","vue_article_vue-project.md":"5d0f04d5","vue_article_vue-node.md":"05bbf374","vue_article_vue-hook.md":"a2599583"}
